logistro/__init__.py
logistro/_api.py
logistro/_args.py
logistro/py.typed
logistro-1.0.12.dist-info/LICENSE
logistro-1.0.12.dist-info/METADATA
logistro-1.0.12.dist-info/WHEEL
logistro-1.0.12.dist-info/top_level.txt
logistro-1.0.12.dist-info/RECORD
