Metadata-Version: 2.1
Name: logistro
Version: 1.0.12
Summary: Simple wrapper over logging for a couple basic features
Author-email: Andrew Pikul <ajpikul@gmail.com>, Neyberson Atencio <neyberatencio@gmail.com>
Maintainer-email: Andrew Pikul <ajpikul@gmail.com>
Project-URL: Homepage, https://github.com/geopozo/logistro
Project-URL: Repository, https://github.com/geopozo/logistro
Requires-Python: >=3.8
License-File: LICENSE
